costlens_mcp/__init__.py
costlens_mcp/bigquery_client.py
costlens_mcp/cost_calculator.py
costlens_mcp/optimizer.py
costlens_mcp/pricing.py
costlens_mcp/schemas.py
costlens_mcp/server.py
costlens_mcp/sql_parser.py
costlens_mcp-1.0.0.dist-info/METADATA
costlens_mcp-1.0.0.dist-info/WHEEL
costlens_mcp-1.0.0.dist-info/entry_points.txt
costlens_mcp-1.0.0.dist-info/RECORD
