Metadata-Version: 2.4
Name: costlens-mcp
Version: 1.0.0
Summary: FinOps MCP Server for BigQuery - Cost estimation, query optimization, and safe execution
Project-URL: Homepage, https://github.com/elie00/costlens
Project-URL: Documentation, https://github.com/elie00/costlens#readme
Project-URL: Repository, https://github.com/elie00/costlens
Author: CostLens Team
License-Expression: MIT
Keywords: ai,bigquery,cost,estimation,finops,llm,mcp
Classifier: Development Status :: 4 - Beta
Classifier: Intended Audience :: Developers
Classifier: License :: OSI Approved :: MIT License
Classifier: Programming Language :: Python :: 3
Classifier: Programming Language :: Python :: 3.11
Classifier: Programming Language :: Python :: 3.12
Classifier: Programming Language :: Python :: 3.13
Classifier: Topic :: Database
Classifier: Topic :: Software Development :: Libraries
Requires-Python: >=3.11
Requires-Dist: google-cloud-bigquery>=3.20.0
Requires-Dist: mcp>=1.0.0
Requires-Dist: pydantic-settings>=2.0.0
Requires-Dist: pydantic>=2.0.0
Requires-Dist: sqlglot>=20.0.0
